openv/__init__.py
openv/constant.py
openv/core.py
openv/exception.py
python_openv-0.1.1.dist-info/LICENSE
python_openv-0.1.1.dist-info/METADATA
python_openv-0.1.1.dist-info/WHEEL
python_openv-0.1.1.dist-info/RECORD
