Metadata-Version: 2.1
Name: python-openv
Version: 0.1.1
Summary: Basically the same as python-dotenv except integrated with 1password.
Home-page: https://github.com/harttraveller/python-openv
License: MIT
Author: Hart Traveller
Author-email: ruling_fiction.0b@icloud.com
Requires-Python: >3.9.7,<4.0
Classifier: License :: OSI Approved :: MIT License
Classifier: Programming Language :: Python :: 3
Classifier: Programming Language :: Python :: 3.10
Classifier: Programming Language :: Python :: 3.11
Classifier: Programming Language :: Python :: 3.12
Requires-Dist: 1password (>=1.0.7,<2.0.0)
Project-URL: Documentation, https://github.com/harttraveller/python-openv/README.md
Project-URL: Repository, https://github.com/harttraveller/python-openv
